 [
    {
      "id": 1,
      "type": 1,
      "name": "Karupatti Coffee",
      "description": "",
      "price": 20,
      "amount": 0,
      "favorite": false,
      "pic": "/./product/Coffee.png",
      "notes": ""
    },
    {
      "id": 2,
      "type": 1,
      "name": "Karupatti Tea",
      "description": "",
      "price": 20,
      "amount": 0,
      "favorite": false,
      "pic": "/./product/karupatti tea.png",
      "notes": ""
    },
    {
      "id": 3,
      "type": 1,
      "name": "Normal Tea",
      "description": "",
      "price": 10,
      "amount": 0,
      "favorite": false,
      "pic": "/./product/normaltea.jpg",
      "notes": ""
    },
    {
      "id": 4,
      "type": 1,
      "name": "Badam Milk",
      "description": "",
      "price": 20,
      "amount": 0,
      "favorite": false,
      "pic": "/./product/Badam Milk.jpeg",
      "notes": ""
    },
    {
      "id": 5,
      "type": 1,
      "name": "Nattu Sakkarai Tea",
      "description": "",
      "price": 15,
      "amount": 0,
      "favorite": false,
      "pic": "/./product/Nattu Sakkarai Tea.jpg",
      "notes": ""
    },
    {
      "id": 6,
      "type": 1,
      "name": "Lemon Tea",
      "description": "",
      "price": 15,
      "amount": 0,
      "favorite": false,
      "pic": "/./product/lemon.jpg",
      "notes": ""
    },
    {
      "id": 7,
      "type": 1,
      "name": "Normal coffee",
      "description": "",
      "price": 15,
      "amount": 0,
      "favorite":false,
      "pic": "/./product/Normal coffee.jpg",
      "notes": ""
    },
    {
      "id": 8,
      "type": 2,
      "name": "Panakarkandu Paal",
      "description": "",
      "price": 20,
      "amount": 0,
      "favorite": false,
      "pic": "/./product/Panakarkandu Paal.jpg",
      "notes": ""
    },
    {
      "id": 9,
      "type": 2,
      "name": "Paruthi Paal",
      "description": "",
      "price": 20,
      "amount": 0,
      "favorite": false,
      "pic": "/./product/Paruthi Paal.jpg",
      "notes": ""
    },
    {
      "id": 10,
      "type": 1,
      "name": "Sukku paal",
      "description": "",
      "price": 20,
      "amount": 0,
      "favorite": false,
      "pic": "/./product/Sukku paal.jpg",
      "notes": ""
    },
    {
      "id": 11,
      "type": 1,
      "name": "Green Tea",
      "description": "",
      "price": 20,
      "amount": 0,
      "favorite": false,
      "pic": "/./product/greentea.jpg",
      "notes": ""
    }
  ]